README.md
main.py
setup.py
stochastis.egg-info/PKG-INFO
stochastis.egg-info/SOURCES.txt
stochastis.egg-info/dependency_links.txt
stochastis.egg-info/entry_points.txt
stochastis.egg-info/requires.txt
stochastis.egg-info/top_level.txt