Metadata-Version: 2.1
Name: stochastis
Version: 1.0.0
Summary: Convert Python code into music to hear algorithms
Home-page: http://github.com/Pebaz/stochastis
Author: http://github.com/Pebaz
License: MIT
Platform: UNKNOWN
